galvanize_auth_api/__init__.py
galvanize_auth_api/clients.py
galvanize_auth_api/connections.py
galvanize_auth_api/errors.py
galvanize_auth_api/info_utils.py
galvanize_auth_api/models.py
galvanize_auth_api-1.0.0.dev2.dist-info/LICENSE
galvanize_auth_api-1.0.0.dev2.dist-info/METADATA
galvanize_auth_api-1.0.0.dev2.dist-info/WHEEL
galvanize_auth_api-1.0.0.dev2.dist-info/RECORD
